py3o.renderers.pyuno-0.5-py2.7-nspkg.pth
py3o/renderers/__init__.py
py3o/renderers/pyuno/__init__.py
py3o/renderers/pyuno/main.py
py3o/renderers/pyuno/office.py
py3o.renderers.pyuno-0.5.dist-info/zip-safe
py3o.renderers.pyuno-0.5.dist-info/namespace_packages.txt
py3o.renderers.pyuno-0.5.dist-info/top_level.txt
py3o.renderers.pyuno-0.5.dist-info/METADATA
py3o.renderers.pyuno-0.5.dist-info/DESCRIPTION.rst
py3o.renderers.pyuno-0.5.dist-info/metadata.json
py3o.renderers.pyuno-0.5.dist-info/WHEEL
py3o.renderers.pyuno-0.5.dist-info/RECORD
