Metadata-Version: 2.0
Name: py3o.renderers.pyuno
Version: 0.5
Summary: A pyuno based driver for py3o
Home-page: https://bitbucket.org/faide/py3o.renderers.pyuno
Author: Florent Aide
Author-email: florent.aide@gmail.com
License: MIT License
Keywords: OpenOffice PDF
Platform: UNKNOWN
Classifier: Development Status :: 4 - Beta
Classifier: Operating System :: POSIX :: Linux
Classifier: Programming Language :: Python
Classifier: License :: OSI Approved :: MIT License
Classifier: Topic :: Software Development :: Libraries :: Python Modules
Requires-Dist: setuptools
Requires-Dist: py3o.formats
